{
  "slug": "british-liberty-established-and-gallic-l",
  "sourcePdf": "British_Liberty_established_and_Gallic_L.pdf",
  "sourcePath": "Jim Renihan Particular Baptist PDFs/Other baptist things/De Fleury, Maria/British_Liberty_established_and_Gallic_L.pdf",
  "pageCount": 57,
  "extractedAt": "2026-04-20T21:07:04.880Z",
  "text": "This is a reproduction of a library book that was digitized by Google as part of an ongoing effort to preserve the information in books and make it universally accessible. http://books.google.com\n\n-- 1 of 57 --\n\n-- 2 of 57 --\n\n-- 3 of 57 --\n\n-- 4 of 57 --\n\n-- 5 of 57 --\n\n-- 6 of 57 --\n\n\\ \\\\JJZ\n\n-- 7 of 57 --\n\nBRITISH LIBERTY ESTABLISHED,\nAND\nGALLIC LIBERTY RESTOFRED;\nI\nOR, THE\nTRIUMPH OF FREEDOM£\nA tPOEM.\nOCCASIONED BY THE\nGRAND REI/OLUTION IN FRANCE,\nM,Dcc,LxxxIx.\n' TH A PROSPECT OF FrHE GLORIOUS TIME WHEN TRUB\nRELIGION AND CIVlL LIBERTY SHALL SHED THEIR\nBENIGN INrFLUENCES OVER THE WORLD.\n. gqnw\"\nFLEUM A N\n. BT MARIAQL\nſ'\n\\ L O N D O N:\n(FROM PETERBOROUGH-HOUSE PRESS)\nPRINTED FOR THE AUTHOR, NO.' 31, JEWIN STREET;\n' AND sonn BY\nJ. MATTHIWS, s'rRAND; n. o. SYMONDS, PATER-NOSTER-Row 5'\n3. NOTT, LOMBARD_ s'rnuz'r; ASH, TOWER summe-r;\nTKOMPSON, OXFORD ROADz AND BY mns. HANCOCK,\nBEACR BTREET, BARBICANS '\nM,OCC,XC' l\n\n-- 8 of 57 --\n l\n'\n/\n.\n\t,. \\\n. v l\n.\n\t\\\n\t*\n'\nI\n-\n\\ \\\n' a\n\t\\ *' r\n' a\nA\t' I\n' 1\n-\n\\\n-\n4\n1\n'\n' '\n' o t l s\n_ n\n' 0\n\\\n'\n' q -\n1\n' \\ ,\n' l\nI\nI '\nI i\n1\n' \\\n! i\n\\\\\nO\n' i\n\n-- 9 of 57 --\n\nSELECT BOOKS K\nON'THE DIGNITY AND PREROGATIVES OF AN\nENGLISHMAN.\n1. A CLEAR Idea of the good old Britiſh Conſti_ tution. xs. per doz.\n2. The Corner Stone of the Britiſh Conſtitution; or, the Golden Paſſage in Magna Charta. Is. 6d. per doz.\n3. The Digniey and Prerogatives of a Frenchman, i ariſing from the new Conſtitution of France, in French and Engliſh. IS. per doz.\n4.. The Dignity and Prerogatives of an Engliſhman z or, the Extenſive Powers and Glorious Privileges of the Com mons of Great Britain. IS. per doz.\n5. The good old Argument for the Divine Inſpiration of the Holy Scriptures. Is. per doz.\nſillſdd by the Bookſtllers in the Title Pair:\n\n-- 10 of 57 --\n v_-_--<.___ _ 4 p I '\n' '\n-\n' ' \\ ' \\\n, . \\ l' '\n0 '\n\t1\nI\n' ' ,-\n'\n'\nA a\n. .\nI\n. _ . 4\t'\n\t\\\n_ l\n\\\n- - p . _ _ I\n\t' _ o ' -\n\tan' 4 . T\t. ' A\n. ' _ * '* n\n\t. * * a\n\t' i a\n\tr \\\n. \\\n\t. _ 1\n- I.- -\\\n'\n\t. \\ . . \\ '\n\ta\n1 r ſ\n\tI 1 .\nV ' a *\n- I\n, o\n\t. '\n\\ -\nI . i 4\n-\t' .\n.\\ J '\n\t\\ ' *\n' l\n. , i\n' A\n- \\\n\tl\n'\n\t*\n\\\n' i .\n>* i I\n4 p\nI\n\tl ' i.\n- . I . l ' n - . l .\nI\nſ I\n\tI l I '\n\n-- 11 of 57 --\n\n[ V ]\nTHE\n* ARGUMENT.\nPART THE FIRST.\nſin ſnvoeation to the Muſt ;-an Addreſs to Britannia ;-ta\nſilſred the Great, as the Founder of Engli/h Lihertyz-u an Allzffion to King John, and the Signing ofMagna\nCharta z-to the Triumphs of England over France, in the Reigns of Edward the Third and Henry the Fifth 3 a Cang'atulatory ſiddreſh to Britons, from a Fiew of the Privileges they now enjoy, from the excellent Con\nſtitutien of this Country, and the mild Adminiſtration of\nKing George the Third z-an Exhertation to watch wer and defend thoſe Privileges ;--and an I-Iymn aſ Praiſe to\nGod as the Guardian of England.\nPſiART THE SECOND\nCommenee: with a Simile of a Traveller relactantly leaving\nArahia the Happy, to travel through ſirahia the De/art 3 a Vice-w of the great-ſſ Part of Europe groaning under\nChains of Tyranny and Opprefflion, and overwhelmed with .\nIgnorance and Popiſh Darhneſs ;--whieh leads to the Ce lehration of the glorious Rewelution in France of 1789.\nſi \\ PART\n\n-- 12 of 57 --\n\nPART THE THIRD.\nſi In Attempt to improve the two former Parts-ſhewing the grand Caafl' of the late Revelation, and the great end to which it leads, from a retrzfizecti'ue l/iew of the Riſe and\nFall of the four great Empires ſpoken of hy the Prophet\nDaniel, and exempliſied hy Dean Prideaux, Rollin, and\nBiſhop Newtonzu-'with a Proſhect of the glorious Time when TRUE RELIGION and CIVIL LIBERTY ſhall\nſhed their Bleſſing: all o'ver the Mrld.\nGALLIC\n\n-- 13 of 57 --\n\n4.\nPREFACE.\nAT a time when the great and important events, which have lately taken place, (events ſo intereſting to Mankind in general, and to the Lovers ofthc\nProteſtant Religion and of Civil and Religious\nLiberty in particular), has fixed the attention, ani mated the paſiions, and deeply impreſſed almoſt every heart, I flatter myſelf that the following Poem will not be altogether unacceptable to the Public.\nIt was not written with. a view to acquire either gain or applauſe; but as the Divine Goodneſs has honoured me with the friendſhip of many moſt reſpectable and valuable perſons, who condeſcend to be pleaſed'with the little effufions oſ my unwor thy pen, it was compoſed to oblige them, and indeed at the particular requeſt of. one of them; a requeſt which was the more agreeable torne, as it was entirely ſuited to my inclination; being, myſelf of French extraction, I cannot but be deeply inte reſted in the great events which have lately taken place in France, although I poſſeſs an Engliſh heart; and therefore the intereſts of my native Country are paricularly dear and valuable to me.---Sh0uld this little\n\n-- 14 of 57 --\n\n4 iv PREFACE. little piece be ſo highly honoured as to meet the ap-e probation oſ my friends, I ſhall be happy 5 ſhould it be any way uſefiJl to young minds, and have a ten dency to impreſs upon them the importance and va lue of the noble privileges they enjoy as Britons, and ' have a natural and unalienable right to as'men; to in\nſpire them with generous ſentiments oſ public ſpirit, and'love to their Country; and, above all, with gratitude to the Divine Author and giver oſ all their bleſſings, and thereby promote, in ſome ſmall de gree, the glory of Gpd; my principal deſign in writing will be abundantly anſwered.l--I flatter myſelf that the public in general, and thoſe in par-7 ticular who are pleaſed to honour me with their friendſhip, will ſuffer the propriety of my intention in writing to cover the many improprieties they may diſcover in the Poem; and that they will do me\n' the juſtice to believe, that, if I poſſeſſed the brighteſt genius and greateſt abilities in the world, inſtead of the little half talent God has beſtowed upon me, it would be my higheſt delight to lay them out for the improvement ofthe riſing generation, and to expreſs my gratitude to my God, my Friends, and my\nCountry.\nMARIA DE FLEURY. jANUARY 6. 1790,\nNo. 31, jEWlN-STREET.\nTHE\n\n-- 15 of 57 --\n\nGALLIC LIBERTY; on, TH E\nTRIUMPH OF FREEDOM.\nL a'\n/\nCOME, heav'nly Muſe, affiſt me while I ſing;\nThy ſweeteſt lyre, thy choiceſt muſic bring:\nCome, warm my heart with thy celeſtial' fire,\nWith nobleſt rapture all my ſoul inſpire ;\nRapture like her's * who ſung the glorious day\nWhen SlSERA became a Woman's prey 3\nWhen FREEDOM triumph'd, and JEHOVAH frown'd 5\nA haughty Tyrant bleeding to the ground.\nFREEDOM's my theme, to celebrate her name,\nO that my lays were equal to my theme !\nThat I could write with an immortal pen,\nAnd trace, with ſteady eye, 5' the ways oſ GOD to Men!'{\n7? Deborah, Judges, Chap. v.\nB BRITANNtA,\n\n-- 16 of 57 --\n\n8 _ GALLlC LIBERTY.\nBRlTANNlA, hail! thou favour'd (been of Iſl'es,\nLong kindly foſter'd by thy Maker's ſmiles'!\n1 When riſing firſt from Ocean's oozy bed,\nHe bade thee rear aloft thy ſtately head;\nBade thy white cliffs tridmphant o'er the main\nThrough all ſucceeding generations reign.\nWhen from the grave, Victorious, JESUS roſe,\nAlmighty Conqu'ror over mighty foes,\nTh' aſcended SAVIOUR claim'd thee for his own,\nAn earlyjewel planted in his crown,\nAnd ſent his everlaſting Goſpel down ;\nDiſperſt the ſhades of Druid night away,\nAnd fill'd thy happy Iſle with evangelic day.\nThen, as his crowning gift, from his right hand\nFREEDOM he ſent, to bleſs thisſſfavour'd land;\nBRITAIN be free! he ſaid; and FREEDOM then\nBecame the darling RXGHT of ENGLISHMEN.\nTo fix her throne, her ſtandard high to rear,\nBehold a long illuſtrious race appear!\nWiſe to deſign, firm to maintain her laws,\nTo bleed, and die, in FREEDOM'S ſacred cauſe.\nALFRED! iſ thy great ſoul can yet receive '\nThe tribute which a g-rateful People give,\nLook down, and liear a Nation bleſs thy name,\nAnd conſecrate to thee immortal fame :\nLook down, and ſee the Temple, all divine!\nThy Sons erected fromithy vaſt deſign;\nThy\n\n-- 17 of 57 --\n\nGALLIC LIBERTY. 9\nThy hands the great foundation laid, and We\nAdmire the Founder of our Liberty :-\nA King ! a Father ! how rever'd a name?\nGo, Kings, and emulate and ſhare the fame l\nNo more fair FREEDOM rnournsw her ruin'd ſanes!\nNo more of barb'rous Gothic rage complains:\nIn Britiſh breaſts ſee Spartan courage flow, i ,\nAnd Roman virtue in their boſoms glow!\nHer ſorrows ceaſe, ſhe, with a placid ſmile,\nClaps her bright wings, and in this ſea-girt Iſle\nDelights to dwell, forgets her ancient ſeat,\nAnd makes this land of light her lov'd retreat.\nSEE a proud Tyrant *, with a crown in view',\nO'er blood and fratr-icide the prize purſue ;\nSee him enthron'd, extend an iron rod\nO'er free-born BRITONS,. and intend his nod\nTo be their law; his ſov'reign will, the bound\nOf right and Wrong.-Is no deliv'rer found P\nNo JUNIUS BRUTUS, who will nobly ſtand\nThe glorious champion of a ſinking land?\nYes 3 I behold ten thouſand heroes riſe,\nI hear their ſhouts, re-echoing, rend the ſkies ;\nI ſee their banners waving in the air,\nThe-founding trump proclaims, that BRITONS dare\n* King john.\n3 2. Defend\n\n-- 18 of 57 --\n\n'to _ GALLlC LIBERTY.\nDefend their ſacred rights thro' toils and death,\nAnd boaſt of FREEDOM with their lateſt breath.\nO RUNNEMEAD ! the great hiſtoric page\nShall celebrate thy name from age to age !\nIn diſtant times, the venerable Sire,\nFeeling his boſom glow with patriot fire,\nShall tell his Sons of thee, and (pointing) ſay,\nRemember, Boys, the memorable day\nWhen here BRITANNlA's valiant Barons ſtood,\nHer nobleſt Sons, determin'd, brave and good;\nTheir cauſe, the cauſe of juſtice, truth, and law:\nThe haughty Tyrant trembled when he ſaw\nTheir gallant hoſt, fear ſtruck the coward pale,\nWhile Heav'n rejoic'd to ſee the RIGHT prevail:\n'Twas here, in ſpite of Hell and all her foes,\nFair FREEDOM triumph'd, MAGNA CHARTA roſe.\nSEE Conqueſt, eagle-wing'd, from Heav'n deſcend,\nBRITANNIA's fleets and armies to attend;\nShe ſhakes her ſnowy plumes, and calls to arms,\nLeading to glory' thro' the dread alarms\nOf horrent war.--GALLIA, thy fields. can tell\nHow many gallant heroes fought and fell,\nTo raiſe the honours of the Britiſh name,\nAnd deep engrave it in the liſts of ſame.\nSee\n\n-- 19 of 57 --\n\nGALLIC LlBERTY. ſi II\nSee weeping CRESSY ſtill lament her day,\nAnd proud POICTIERS the Victors might diſplay;\nSee AGINCOURT immortal laurels bring,\nTo wreath the brow of ENGLAND's youthful King.\nNo more let mortals truſt in mortal might,\nThe God of Battles muſt decide the fight;\nLet the proud boaſter learn to boaſt no more,\nBut, with our HENRY, wonder and adore.\nIN vain does Hell and Rome conſpire to pour\nBlind papal darkneſs on this happy ſhore;\nIn vain aſpiring tyrants riſe and rage,\nBRITAIN ſhall ſtill be free from age to age.\nHeav'n puffs at their deſigns from his high throne,\nAnd, frowning, ſhakes their mighty Babels down 3 \".\nAt the dread ſound of his avenging ire,\nA JAMES ſhall abdicate, a CHARtEs expire!\nA CROMWELL and a WILLIAM ſhall appear\n(Hail, glorious names! hail, names to BRITAIN dearl)\nAnd, like an oVerwhelming whirlwind, ſweep\nDeſpotic monſters to their native deep ;\nWhile Antichriſt and Tyranny ſhall fall,\nAnd FREEDOM, BRITISH FREEDOM, triumph over all!\nBLiEST Halcyon days now reign-let BRITONS ſing,\nNo more they groan beneath a tyrant King;\nNo\n\n-- 20 of 57 --\n\n12 GALLIC LIBERTY.\nNo more they ſmart beneath th' oppreffive ſwor --\nMild is the ſceptre ſway'd by GEORGE the THIRD* !\nIn her full ſplendor ſacred Truth appears,\n'\nAnd Peace and Plenty crown our happy years.\nLate a black cloud o'er-hung the Britiſh ſky,\nThe thunders roll'd, the rattling ſtorm drew nigh,\nBRITANNIA'S boſom heav'd the trembling ſigh;\nWhen, lo ! her ſun aroſe with cheerful ray,\nShone thro' the tempeſt, drove the ſhades away; _\nO'erwhelmffd with joy, ſhe tun'd her voice to ſing ct The GOD whoſe ſov'reign pow'r reſtor'd her King!\nZion too, ſhouted 3 Zion caught the flame,\nAnd ſung hoſannah to the gracious name\nWhoſe condeſcending eye beheld her care,\nAnd. gave her much-lov'd Sov'reign to her pray'r.\nLong may th' imperial diadem adorn\nHis royal brow; may GEORGE, a BRITON born, i Long over free-born BRITONS live to reign,\n'To guard their rights, their liberties maintain ;\n* Let it be remembered here, that I write ofthings in a general point oſview.\nItis to be lamented, that, notwithſtanding the excellence of the Britiſh Conſti tution, notwithſtanding the mild diſpoſition of our preſent Sovereign, yet there exiſt in this Country ſome very arbitrary Courts of Judicature 5 and there alſo exiſt ſome men ofeorrupt minde, who, putting their-own glaſſes upon good and wholeſome laws, are not aſhamed to deem ſpeaking the Tuu-rn libellous; ſo that, even in theſe days of Freedom, there are very reſpcctable perſons, loya]\nſubjects, pining in an odious priſon with felons and murderers, whoſe only. crime is ſpeaking the Txu Tn. When will Engliſh Liberty triumph oVer theſe oppreſſions P\nMay\n\n-- 21 of 57 --\n\nGALLIC LIBERTY. 13\nMay he the Father of his People be,\nAnd prove their love, their laws, and liberty,\nThe firmeſt, beſt ſupporters of his throne.\nThe choiceſt, brighteſt jewels of his crown,\nSay, Muſe, her name, who reigns with ſov'reign ſway\nIn Britiſh hearts i Record the happy day,\nWhen CHARLOTTE, like the ſun, aroſe to bleſs\nAnd crown a King and Pe0ple's happineſs.\nWife, great, and good, long may ſhe live to prove\nThe darling object of three kingdoms' love 5\nWhile big-ſwoln Envy turns aſham'd away,\nAnd Slander's forked tongue finds not one word to ſay.\nBRITONS rejoice, no chains are forg'd for you,\nTo break your ſpirit, and your minds ſubdue;\nNo dreary caves exclude the beauteous light,\nAnd bury heroes in perpetual night;\nNo IRON CAGES, no BASTILES ariſe,\n-To curſe the groaning earth, inſult the ſkies;\nNo Widows weep, no Orphans mourn in' vain\nHuſbands and Fathers ſnatch'd away, or ſlain,\nBy cruel Policy. Here FREEDOM reigns,\n_ And law and juſtice hold the ſacred reins\nOf ENGLAND's Government. O BRITONS raiſe\nTo heav'n's high King a monument'of praiſe !\nMark well your bleſſings, ſee how high they riſe,\nDeep in your hearts record, and learn to prize\nThe\n_L-'I\n\n-- 22 of 57 --\n\n14.' GAL'LIC LIBERTY.\n_-_-______-\n-\nThe noble privileges you poſſeſs, 'I\nBoth civil and religious happineſs: 1 _, z; a\nInform your children, let the riſing youth\nBe taught to ſtudy this important truth;\nFREEDOM is ſtill (oppoſe who will or can)\nThe noble birth-right oſ an ENGLISHMAN.\nO l hold it faſt, than eaſe,- than life more dear,\nAnd bold and wiſe in its defence appear;\n'VVatch o'er your rights, with more than Argus' eyes,\nLeſt force or fraud deſpoil you of the prize;\nTo diſtant ages, to the end of time,\nHand it unſullied-let this favour'd clime\nLong reign the mighty Empreſs of the ſea,\nRenown'd for TRUTH, for PEſſAca, and LlBERTY.\nLet diſtant ages with the preſent join,\nTo raiſe, in numbers ſweetla ſong divine;\nA ſong of grateful praiſe to BRITAIN's GOD,\nWho breaks our en'mies with an iron rod;\nBut ſways a golden ſceptre o'er this land,\nAnd keeps it ſafe in his Almighty hand. 3\n(fit .\nHAIL, BRITAm's GODl BRITANNIA bows to thee,\nThou Sov'reign Author oſ her Liberty; p 'Twas thou diſpell'd the (hades of papal night,\nAnd ſhed abroad the beams of Goſpel light.\nþThy Sov'reign love has made her ſtill thy care,\nThy wrath hath cruſh'd her Tyrants in deſpair;\nFrom\n\n-- 23 of 57 --\n\n'G-ALLIc LIBERTY. 15\nFrom thee her ever-new ſalvation ſprings,\nGreat Setter-up and Putter-down of kings :\nLet earth and ſea conſpire to ſpeak thy praiſe,\nLet old and young a ceaſeleſs anthem raiſe ;\nLet King and People ſwell the triumph high,\nAnd ſhout hoſannahs thro' the echoing ſky.\nAnd ſtill, oh l, ſtill may we enjoy thy ſmile,\nAlmighty Guardian of this happy Iſle;\nO! ſend thy Spirit down to crown thy truth;\nLet venerable fires, let blooming youth,\nWon by the pow'r of thy Victorious word,\nTo holineſs and happineſs reſtor'd,\nTake at a SAVIOUR'S feet their humble place,\nThe willing ſubjects of Almighty grace:\nLet error flee, let truth and juſtice reign,\nLong as BRlTANNIA's compaſs'd with the main ;\nLet Britiſh hearts ſtill glow With patriot fire,\nTill ſun, and moon, and ſtars, and worlds expire. c \\ * XPART'\n\n-- 24 of 57 --\n\n16 CALLIC LIBERTY.\nPART THE SECOND.\nFROM the fair fields of Araby the bleſt,\nWith ſpicy groves and conſtant verdure dreſt;\n. Where Nature's richeſt ſruits proſuſely grow,\nAnd cooling [treams in pleaſing murmurs flow;\nHow the loath trav'ler, with reluctant feet,\nQuits the) lov'd ſoil, his favourite retreat,\nT'explore the horrors of the wilderneſs,\nNew ſcenes of woe and multiply'd diſtreſs ;\n'Midſt burning ſands, where no cool ſprings ariſe,\nBut oft the fainting trav'ler thirſts and dies ; i\nWhere ſavage bands rapacious roam for prey,\nAnd whirlwinds ſweep whole caravans away:\nSo from the Land oſ Liberty and Light,\nWith drooping wing, my Muſe muſt take her flight z\nShe for a While muſt lay her triumphs by,\nAnd ſing with plaiſintive voice, and view with weeping eye\nO'er mighty realms deep ſhades oſ night prevail, ſ i\nMyſterious Babel ſpread her gloomy veil\nO'er millions oſ immortal minds, who lay\nFar from the borders of celeſiihl day;\nAbſorpt in ignorance and flaviſh fears,\nThro' the long period oſ a thouſand years ;\nTheir gen'rous ſpirit curb'd, their noble fire,\nSuch as the love of FREEDOM muſt inſpire;\nQiench'd\n\n-- 25 of 57 --\n\nGALLIC LiBERTYþ 17\n\\\nWench'd by a [weeping flood, a deluge wild,\nOf arbitrary pow'r, chafing each mild\nAnd amiable virtue far away, ,\nWhile horrid Tyranny her ſrowns diſplay.\nSEE the proud purple Deſpot waveihis hand,\nTh' important ſignal of ſupreme command; ſi\nHis will'the law of millions 5 at his nod\nThey bow and tremble, as a demigod;\nHe ſhines illuſtrious, thinks a nation born -\nTo ſwell his triumph, and his pomp adorn.\nJuſtice and Virtue, from his preſence driv'n,\nWit his domains, and ſeek their native heav'n;\nMercy and Truth retire, and in their ſtead . \\\nSee treach'rous Falſhood raiſe her hateful head;\nAdult'rous Luſt, inſatiate thirſt for gold,\nAnd Rapine her rapacious jaws unfold :\nAmbition forms a thouſand plans to riſe;\nA thouſand arts employs to gain the prize; p '\nThe glitt'ring prize, purſu'd with ardent zeal,\nAnd ev'ry motive, but the public weal,\nAttain'd, the giddy pageant of an hour\nBaſks in the ſunſhine of a Tyrant's pow'r 3 i - i\nHis ſmile exalts him, but, anon, a frown\nTumbles the wretch and all his honours down.\nFROM age to age this aweful purſe hath ran,\nAnd in the SLAVE been loſt the rights of MAN:\nC Z\n\n-- 26 of 57 --\n\n18 GALLIC LlBERTY.\nIf e'er a Patriot felt his boſom move\nWith that great principle, his country's love,\nA noble ſpark of true heroic fire,\nAnd durſt to liberty and truth aſpire,\nSee priſons riſe, ſee dungeons ſink for him,\nAnd racks and wheels muſt tear him limb from limb z p While ſilent multitudes their tears ſuppreſs;\nNor dare in ſepret ſighs their grief expreſs, A\nLeſt keen ſuſpicion, with her jealous eyes, -\nShould read rebellion in their ſecret ſighs;\nShould ſacrifice to political fears,\nAnd in their martyr's ruin mingle their's.\nEACH gen'rous effort of the ſoul to bind,\n. And rivet fetters on the free-born mind,\nA thouſand terrors riſe, contriv'd in 'Hell\nHow black, how horrible, what tongue can tell?\nO'er hapleſs realms ſtretch out their dark domain,\nAnd in BASTILES and INVHSITIONS reign. i\nThe mighty bulwarks of deſpoticpow'r,\nWhere Tyranny enthron'd, with hideous roar,\nDarts her grim horrors round a frighted ſtate,\nA NATION trembles, cruih'd beneath the weight;\nProſtrate receives, and patient bears the ſtroke, A\nAnd groans ſupine beneath the iron yoke.\nSuch were thy chains, O GALLIA ! while the ſun\nFrom age to age his deſtin'd periods run; r i While\n\n-- 27 of 57 --\n\nGALLIC LIBERTY. 19\nWhile pow'r deſpotic hurl'd her thunders round,\nA thouſand generations felt the wound.\n'TIs paſt, the hour is come, 'the glorious hour,\nWhen France no more ſhall own a Tyrant's pow'r;\nThe day appears, the grand illuſtrious day,\nDiſperſing night with all her ſhades away.\nO come, fair FREEDOM ! daughter of the ſkies,\nTo thee a Nation lifts their longing eyes;\n'Tis thee they invocate, with patriot breath,\nDetermin'd to be free, or ſleep in 'death ;\nExtend thy gracious ſway from ſhore to ſhore,\nAnd reign till ſuns ſhall riſe and ſet no more.\nFROM ſleep, from ſloth awake l (a hero cries)\nYe noble Franks : Echo aloud replies,\nFrom ſleep, from ſloth awake! Shake off your chains,\nTo dwell with ſlaves fair Liberty diſdains;\nShe reigns o'er MEN. No more ſupinely lay\nHugging your fetters, let your deeds diſplay\nThe vigour of immortal minds; rouſe, rouſel\nAnd at fair FREEDOM's ſhrine repeatiyour vows ;\nLive free, or nobly ſtamp it on your graves; _,\nAwake, ariſe, or be for ever ſlaves l '\nHE ſpake, and thro' the Nations ſwift it flew\nThe Nations heard, the Nations triumph'd too;\nWith noble zeal, a thouſand tongues repeat\nThevoice of HEAv'N, of FREEDOM, and FAYETTE.\nSee\n\n-- 28 of 57 --\n\n'20 ' GALLIC LJBERTY\n..-.-_'\\_.-..n\n.-..w-<u w._..__.__..-._.___-_-..<\nSee from Americ's ſhore the Hero come,\nAnd brings a noble band ofworthies home ;\nPerfidious policy had ſent them forth, '\nThey ſtudied FREEDOM in the hoſtile North.Now ſafely landed on their native ſhore, i\nThey muſt be free, they will be ſlaves no more ſ\n'While gen'rous BRIrONs ſcorn a mean revenge,\nAnd leave their wrongs for Heaven to avenge.\nExulting ſee the GALLIC heroes come,\nAnd bring the ſweets of Britiſh FREEDOM home;\nThey ſaw in FREEDOM'S cauſe her Sons expire,\nAnd, lo! their boſoms caught the gen'rous fire;\nThey ſee their Country bound in flaviſh chains,\nThey ſee her bleeding at a thouſand veins;\nTheir hearts expand with noble zeal to ſave,\nOr in her ruins form themſelves a grave. a Let France awake to FREEDOM i\" (FAYETTE cries);\n[9'\n\" Let France awake around the Nation flies ;\nVVinds waft the voice afar, and who's ſo bound ſ\nIn ſlaviſh fetters, not to hear the ſound?\nWhat heart ſo ſpiritleſs, ſo ſunk in fears,\nAs not to glow with ardour when he hears\nThe call to Liberty? The noble fire\nCatehes from heart to heart; the hoary Sirc,\nAnd ruddy Boy, alike its rays inſpire: i\nThey hear l they ſtart l they come I fair FREEDOM'S call\nRevives the ſpirit of the ancient GAUL ; i\nThe ſleeping Lion's rous'd, he paws the ground,\nHe ſhakes his manc, his eye darts lightning round. i . _.___.__\n\n-- 29 of 57 --\n\nGALLIC'LIBERTY. 21\nMWJJLMM'FV=TFT*:*'F'W®M'*TZ *'\nLet Tyrants-tremble, while his awful roar\nConfuſion flings on arbitrary pow'r;\nTo eaſtern climes let deſpotiſm flee,\nEuropean boſoms pant for Liberty;\nAn inj ur'd People claim the rights of men,\nA mighty good, well bought with preſent pain;\nHeav'n looks propitious down, reſolv'd to bleſs\nAnd crown the glorious ſtruggle with ſucceſs. ' *\nFROM Eaſt and Weſt, from North and South, behold _\nA band of worthiles come z in war not bold\nAlone to execute, but wiſe to plan,\nAnd mode] laws of Empire worthy Man.\nOn every brow deliberation ſits,\nAnd public care and prudence, as befits\n* The Senate of a mighty Nation, met\nTo form anew, and organize the State.\nZeal gives their councils life, while caution wards\nA thouſand dangers, circumſpection guards\n(A faithful centinel) their country's love,\nThe noble ſpring which all their actions move.\nSee love to FREEDOM every heart inſpire,\nSee every boſom glow with warm deſire,\nTo break their Country's chains, and ſet her free,\nTo taſte the golden fruits of Well-earn'd Liberty;\nHail, Patriots ! hail I th' aſtoniſh'd World admire,\nAnd catch a ſpark of your heroic fire;\nFrom heart to heart it'runs, from land to land,\n,And kingdoms big with expectation ſtand,\n\n-- 30 of 57 --\n\n__..n_-_....\n-'.--1\nF-'c\n- -* ' A - ---\"'_-__\n22 GALLIC LIBERTY'A\nTo ſee the glorious day when France ſhall be\nEmancipate from chains and ſlavery ;\nWhen the foundation which your wiſdom laid,\nSolid and firm, in edual poiſes weigh'd,\nShall in a noble ſuperſtructure riſe,\nAnd FREEDOM's glorious temple greet the ſkies;\nWhen Tyrants baniſh'd from the realms of day,\nAnd lawleſs rule for ever ſwept away,\nGALLIA no more ſhall under bondagc groan,\nBut boaſt a Conſtitution like our own*.\nThen ſhall the monumental braſs declare\nWho the great FATHERS of their Country were;\nWho dar'd ſtand forth in the important hour,\nAnd reſcue France from arbitrary pow'r:\nYour Sons ſhall tell their Children-they ſhall own,\nAnd make your names to unborn ages known:\nGo on then, Heroes, may a hand divine\nDirect, complete, and crown the grand deſign.\nNOR theſe alone, tho' pillars of the State,\nIn wiſdom, council, erudition great;\nThe noble ardour runs from ſoul to ſoul, i _\nBreathes in each part, and animates the Whole.\nThe artizan lays his mechanics by\nIn FREEDOM's cauſe, his ſkill in arms to try;\nStudents forget their books, Merchants their gains,\nSelf-love expires, and PUBLIC SPIRIT reigns. n'am'\nJ-nu *' The Britiſh. s\nCC\n-< -> *.--.We--- _.\n\n-- 31 of 57 --\n fffiw\nſing-51.'\nGALLIC LIBERTY.\nSee Huſbandmen forſake the plough, and ſtand\nRenowned champions for their native land,\nLike Rome's fam'd CrNCINATUS*.\nAround their Country's glorious ſtandard throng;\nWhile thoſe, by palſied limbs forbid to come,\nChain'd by 'diſeaſe to an ignoble home,\nPant for the field, and bid their ſons ariſe,\nAnd nobly die, or win the darling prize.\nThe martial bands, long train'd to war and arms,\nInur'd to fierce BELLONA's dread alarms ;\nThe ſcourge of FREEDOM, Tyrants hope and boaſt,\nWhoſe ſceptre's guarded by an armed hoſt,\nNot by their ſubjects love-Shall theſe oppoſe\nAnd meet their Fathers and their Sons as foes,\nAnd plant their daggers in their Country's breaſt?\nTheir wretched Country, long with ills oppreſt l\nNow, when a great ſalvation's near in view,\nShall theſe, her cruel Sons, their hands embrue\nIn her delivjrers blood? Oh! no; the fire\nOf patriot zeal their manly breaſts inſpire;\nTheir noble legions ſhout for Liberty,\nAnd ſwear that GALLIA henceforth ſhall be free. _\nNor is the love of Liberty confin'd,\nOr martial ardour, to the manly mind ;\n_ In FEMALE boſoms ſee the flame ariſe,\nGlow in their hearts, and ſparkle in their eyes:\nWith Amazonian courage, lo! they quit\nDomeſtic trifles, and the ſtill retreat,\n* A famous Roman General. See Rollin's Ancient Hiſtory.\nD\n'\nOld and young\nFor r\n\n-- 32 of 57 --\n\n24. \\ GALLIC LIBERTY.\n/\nFor noiſe and buſtle, all the din of war,\nWhere wounds and terrors, death and dangers are;\nTo curb the bounding ſteed, to wield the ſpear,\nAnd all the thunders of the fight to hear.\nThis is thy triumph, ſacred Liberty;\nWOMEN and PRIESTS, inſpir'd by love of thee,\nLay by their weakneſs and timidity;\nThey ſhine in arms, and let the Nations know\nThey ſhun no danger, and they fear no foe.\nTHUS bold, thus firm, when a Whole People riſe,\nBreathing one ſpirit, valiant, ardent, wiſe,_\nWhat can reſiſt P-The mighty torrent ſweeps\nGuilt and Oppreffion to their native deep's 5\nPlucks Uſurpation from her ancient throne,\nAnd all the tools of Deſpotiſm down:\nWhile Virtue, Law, and Juſtice, once again\nCall'd to new life, begin their happy reign.\nNo more a long inſulted People feel\nThe fearful terrors of a proud BASTILE;\nAwak'd to vengeance, lol their fury podrs\nDeſerv'd deſtruction on thoſe hated tow'rs;\nTh: bellowing cannon ſhake the horrid walls\nHark! with a mighty craſh, the wide-ſpread ruin falls.\nWelcome, ye wretches, long inur'd to lay\nIn chains and darkneſs, where no glimm'ring ray,\nNo cheerful beam of heav'nly light appears,\nCondemn'd to pine away the tedious years i.-.-...-__.v._.-.;..-_-<\n.-._eva.\n---------_--- MT\n\n-- 33 of 57 --\n\n_ >__W*'*\nMT _\nGALLIC LIBERTY. 25\nIn night, in damps, in all the depths of woe,\nJVhere no ſoft ſoothing rills of comfort flow;\nWelcome! oh! welcome to the new-found day!\nFair FREEDOM comes to wipe your tears away,\nTo burſt your chains, to bid you live again,\nAnd taſte the balmy bleſſings of her reign!\nFREEDOM for you a patriot People won,\nRiſe from your dungeons and enjoy the ſun.\nHAIL, GALLlA! may thy noble Sons go on,\nAnd crown the work they have ſo well begun;\nWiſe, bold, and ſteady, may they perſevere,\nKnit in firm union, and unmov'd by fear 5\nRiſing ſuperior to ſurrounding foes,\nTill Peace, ſweet Peace, ſhall all her Charms diſcloſe,\nAnd the rude horrors of the ſtorm compoſe.\nThen ſhall your noble toil be richly crown'd, _\nCommerce and Plenty ſhedding bleſſings round;\nWhile Juſtice, Virtue, Truth, a ſacred train,\nOffspring of Liberty, ſhall riſe and reign fſſ\nTo diſtant ages, and enroll the name\nOf this grand azra in the liſts oſ ſame 5\nYour free-born Sons ſhall guard their happy realm,\nAnd future NECKARS riſe to guide the helm.\nFIR'd by the great example, ſee it flies\nSwift as a darting meteor thro' the ſkies ;\nThe noble conteſt ſpreads ſrom ſhore to ſhore,\nMen feel their rights, and will be flaves no more;\nD 2 ' iThe .,__ .__-_.l\n\n-- 34 of 57 --\n\nG ALLIC LlBERTY.\nThe Belgic legions rouſe, and call to arms ;\nGermanic Cities ſhake with rude alarms; 1 -. '\nCaſtillianiboſomsl feel' the riſing flame, 7\nThey lift their hopes to Heav'n, from whence it came,\nAnd ſigh for Liberty-From Heav'n's high King\nFair FREEDOM comes, deſcending with ſwift wing,\nTo crown the brave.-Hark! DESPOTISM groans,\nAnd TYRANTS tremble on their tott'ring thrones 5\nPale SUPElRSTITION droops with panic fear,\nShe feels and niourns her diſſolution near;\nThe ſhades retire, the welcome morning ray\nProclaims the glad approach of heav'nly day.\nGo on then, heroes, may your boſoms feel\nEncreaſing ardour for the public weal ;\nMay prudent Councils guide your grand deſigns,\nAnd Reſolution arm your gen'rous minds.\nFirm, wiſe, and valiant, to maintain your laws,\nHe nobly dies who dies in FREEDOM's cauſe.\nWhere'er the ſun beholds a Nation bound\nIn chains ignoble, may the glorious ſound\nOf your high/deeds with emulation fire\n' Each virtuous Youth, each venerable fire,\n-_\nTill from the earth deſpotic ſway be driv'n,\nAnd TRUTH and REEDOM, eldeſt-born of Heav'n,\nErect their banners high the world around,\nTriumphant over all, with conqueſt crown'd.\nThen ſhall ſweet. Peace her ſofteſt bleffings bring,\nThe free-born Muſe ſhall tune her choiceſt ſtring,\nAnd Heav'n and earth ſhall one grand chorus ſing.\n7 1 PART\n\n-- 35 of 57 --\n\nGALLIC LIBERTY. 27\nPART THE THIRD.\nWHILE round the world the rude alarms of war,\nDiſcordant, ſounds with harſh ungrateful jar 3\nFrom realm to realm the ſtrange commotion flies,\nAnd the hoarſe trump ſalutes the echoing ſkies:\nWaving the ſpear of death, with horrors crown'd,\nThe daemon of deſtruction ſtalks around 3\nTen thouſand terrors march on either hand,\nAnd Deſolation flies from land to land '\nCloſe in his rear, while Empires riſe and fall, l\nAnd CHANGE and REVOLUTION threaten all\nCome thou, my ſoul, and in the land of peace,\nWhere FREEDOM reigns, improve the hour of eaſe ;\nTo the lone cot retire, the humble cell,\nWhere ſweet content and meditation dwell;\nThere liſten to the noiſy clang of war,\nAnd view the horrors of the ſtorm from far;\nAnd aſk 'from whence theſe awful wonders riſe,\nThat ſhake the affrighted earth, and rend the ſkies\nWith fierce convulſions P-Whence the ſecret ſprings\nThat move and actuated all created things P\nThe hand that guides, the eye that views the whole,\nOf this great UNIVERSE, the mighty SOUL,\nDiſpoſing all eventSP-Or do they flow\nFrom chance? Is chance great arbiter below?\nDo\n.-.\n.,,___.\n\n-- 36 of 57 --\n n.--** n'e-rfi'ſrwn-w-c-MWu-W-WWa.H.....__..._\n28 ſſ .-eALL1e LIBJZRTY'.\nDo all things wait upon the will of Kings?\nAre earth's proud potentates ſuch mighty things,\nThat with a frown they can a world embroil,\n'And huſh the tumult with their magic ſmile?\nBy Man's proud will are crowns and ſceptres hurl'd, '\nAnd like a plaything toſs a frighted world?\nLo! from the ſkies deſcends a heav'nly ray,\nBright with the ſplendo'urs of celeſtial day,\nBeyond a thouſand ſuns, my doubts to clear,\nIllume my mind and diflipate my fear\nHail, REVELATION! ſource of ſacred light, a\nThy glorious beams diſpelling mental night, -\nThe grand inquiry ſolves-all, all is right.\nJEHOVAH reigns, let Heav'n and earth adore,\nLet angels bow, let mortals boaſt no more 5\nBut l'ow in duſt with awful wonder fall,\nAnd own JEHOVAH--JESUS Lord of all.\nHe reigns triumphant, let his people ſing,\nZion rejoice, and glory in her King;\nHigh on his Holy Hill he reigns ſupreme,\nLet univerſal Nature worſhip him.\nWhen from rude chaos, and the womb of night,\nHis potentwfiat 'call'd celeſtial light,\nAnd bade a univerſe xof wonders riſe,\nFixt the firm earth, and ſpread the ſtarry ſkies;\nHis mighty mind then fixt the period/s ſure,\nEarth's future riſing Empires ſhould endure;\nThe grand reſolves of his infinite mind\n'Time brings to view, eternity defign'd\n\n-- 37 of 57 --\n\nGALLrc LI'BERTY'. 29\nStill KING 'of KINGS and LORD__of LORDS he reigns,\nAnd, uncontroul'd, his ſov'reign right maintains;\nRules over all, ſupreme diſpoſer ſtill,\nAnd worketh all things as his righteous will\nDetermines. Clouds and darkneſs mark his way,\nThe whirlwind and the ſtorm a GOD diſplay;\nDivine perfection ſhines-in all his ways,\nAlmighty power and ſtupenduous grace;\nWiſdom and juſtice, truth and ſmiling love, '\nDirect his councils, all his actions move. .' r\nOf all the creatures, all the worlds he made', - - -\nThe government is on his ſhoulders laid;\n_In vain does Hell and human pride combine\nHis grand deſigns by their's to countermine.\nThey boaſt in vain, he reigns triumphant ſtill, -\nHis arm of ſtrength ſhall execute his will ;\nThe rage'of Hell and human pride ſhall join '\nAs engines to fulfil his great deſign\nThat muſt prevail, and, whatſoe'er oppoſe,\nNo diſappointment, no prevention knows. i *'\nS/ee pr0ud'Aſſyrian Monarchs ſhake the world, see their wide Empire into darkneſs hurl'd;\nA lofty throne the Medo-Perſian rears,\nTill'fierce in arms the conqu'ring Greek appears:\n,He like a meteor ſhines, the ſudden blaze\nStrikes the affrighted earth with dread amaze;\nLo! he diſſolves in air, his train expires,\nAnd Roman boſoms catch his falling fires.\nImperial\n_.._.._-M..._-_'Ki\n\n-- 38 of 57 --\n\n30 GALLIC LXBERTY.\n-..=-._a-_.-..Z.,zz:\n_ Imperial Rome, before whoſe potent ſway\nKings veil their glories, Empires fade away;\nIt roſe, it ſhone awhile, in ſplendor bright;\nIt ſunk, it fell, o'erwhelm'd with Gothic night.\nBut ſee a nobler Monarchy ariſe,\nSpread o'er the earth, and ſhoot beyond the ſkies 3\nAn everlaſting kingdom, which ſhall know\nNo diſſolution, but ſhall riſe and grow\nTo boundleſs domination, and endure\nWhen ſuns and moons ſhall riſe and ſet no more.\nThis DANIEL ſung *, when, with'enlighten'd eyes,\nHe ſaw the great Prophetic Viſion riſe;\nFour mighty beaſts from out the raging main\nSucceſiive riſe, ſucceffive fall and reign.\nTo Babel's haughty Builder this was ſhewn-ſi\nIn dreams of night he ſaw the myſtic ſtone\nCut without hands, earth's wide dimenſions fill,\nSubduing all things to his ſov'reign will ;\nExtending boundleſs ſway from ſhore to ſhore,\nWhen death, and ſin, and time, ſhall be no more.\nFIRM as the throne of GOD, his great decrees\nShall ſtand, and changeleſs as his nature is;\nHrsſi SCRIPTURES make his mighty purpoſe known,\nThe hidden ſecrets of th' eternal throne\nTo Man revealing; while his arm of pow'r,\nO'erruling all things, in the appointed hour,\n-.====-r;'=.\n*= Daniel, 7th Chap. See Rollirſs Ancient Hiſtory, and Biſhop Newton's\nDiſſertations on the Prophecies.\nFulſils\n\n-- 39 of 57 --\n\nGALLIC LIBERTY. 3!\nFulfils the grand PREDlCTION, and diſplays\nA God of Vengeance, or a God of Grace.\nHis Providence fulfils his great deſigns,\nIn and thro' all immenſe PERFECTION ſhines\nWhen thus he owns his truth by ſov'reign pow'r,\nEarth ſhakes, Hell trembles, and the Heav'ns adore.\nBe ſtill, then, O my ſoul! JEHOVAH reigns,\nAnd all is well, for all thy GOD ordains ;\nTho' tumult and diſtraction roar around,\nAll ſhall with ſweet tranquillity be crown'd\nAll ſhall exalt the glories of thy GOD,\nHis golden ſceptre, and his iron rod;\nShall raiſeſi the honours of thy SAVIOUR's name,\nAnd thro' a wond'ring world ſhallſpread MESSIAH's fame.\nSEE in impervious ſhades the Nations ſit,\nBlack glooms aſcending from the ruthleſs pit z\nIn papal darkneſs bury half the world,\nThe bloody flag of Antichriſt unfurl'd;\nI/Vhile thro' long ages, ſee the Kingdoms join '\nT'erect his throne, and ſtamp him half divine,\nAnd in GOD's holy place the idol beaſt inſhrine.\nBut, In! 'tis written, Antichriſt ſhall fall,\nEarthqu'ake and fire conſume and ſwallow all\nHis boaſted glories, thunderbolts of wrath\nShall drive him head-long from the groaning earth\nTo fathomleſs perdition, there to weep\nAnd howl for ever in the boiling deep. a The\n\n-- 40 of 57 --\n\n32, GALLIC LIBERTY.\"\n--.;-F'*':*r_-.r-:*7**-.\nTh' enlighten'd Kingdoms ſhall unite their pow'r,\nShall hate and deſolate the ſcarlet whore; . i\nNo more her valials, they ſhall riſe and ſing\nSalvation to the everlaſting King,\nWho reigns o'er Heav'n and Earth with ſov'reign ſway,\nAnd bleſs him for a glorious Goſpel-day.\nBIG with the joyful hope, the glad'ning Muſe\nLooks round, with cheerful eye the proſpect views ;\nThe preſent proſpect, ſees a hand divine\nIn all the great events of eighty-nine ;\nShe ſees JEHOVAH riding on the ſtorm, i His word and gracious purpoſe to perform;\nHe ſpeaks, 'tis done; the flumb'ring Nations rouſe,\nThey pant for Liberty, and pay their vows\nAt FREEDOM'S altar. Here the work begins, rThe dawn appears, the welcome morning ſhines,\nOf an illuſtrious day. Come, ſtretch thy wing,\nIVly vent'rous Muſe; come ſoar aloft, and ſing 1\nOf future wonders, which ſhall ſoon ſurpriſe\n_Th' aſtoniſh'd earth, and fill th' adoring ſkies\nVVith I-Iallelujahs. May the h/Iuſe preſume,\nWith ſacred awe, to ſing of things to come?\nShe may ; her hand divine prediction holds, 1\nThe word of truth futurity unfolds;\nShe leans by faith on that unerring guide,\nNo falling prop, no fluctuating tide,\nBut\n> MWA__ .\n\n-- 41 of 57 --\n\nGALLIC LIBERTY. ſſ\nBut ſolid rock, firm baſis. With one eye\nShe views the earth; the other, lifted high, z\nPierces thro' all things to th' eternal throne,\nOf him who-calls ten thouſand worlds his own:\nShe ſees his pow'r fulfil his word, and then '\nMay ſafely ſing of future times to Men.\nSEE from the ſkies ſweet LrBERTY deſcend,\nThe Nations hope, the groaning captive's friend,\nTo bleſs the world, to bid the exile come, i\nThe mourning exile to his long-loſt home:\nBut not alone ſhe comes, a heav'nly ray,\nA beam of radiance from the ſource of day,\nShines round her ſteps; no more ſhall fetters bind, _\nAnd chains of darkneſs hold th' immortal mind.\nTruth, like an angel, wings her way from Heav'n,\nThe beſt, the nobleſt gift to mortals giv'n;\nBefore her pow'rful beams, ſee, ErrOr flies;\nAnd vanquiſh'd' Superſtition faints and dies;\nDown from his throne, where long exalted higher\nThan all on earth call'd God, doom'd to expire,\nAntichriſt, like a falling ſtar, deſcends,\nSwept from his ſeat, 'his proud dominiorr ends 5\nXVhile Truth aſſumes the chair, divinely bright,\nHer ſunlike glories diffipate the night;\nMillions, who ſat in darkneſs, bleſs the rays,\nRiſe from the gloom, and ſing triumphant grace.\nE 2 The\n\n-- 42 of 57 --\n\n34. GALLIC LIBERTY.\n\\\nThe glorious day draws near, on Time's ſwift wing\nIt comes, when Sion's everlaſting King\nShall make his pow'rful arm and wonders known,\nAnd claim the diſtant Kingdoms for his own.\nTh' enlighten'd Eaſt ſhall ſcorn MAHOMET'S name,\nCharm'd by the ſplendor of EMMANUEL's fame;\nShall throw aſide their Alcoran as droſs,\nThe ſilver creſcent bowing to the croſs;\nShall bind his Goſpel to their raptur'd breaſt,\nAnd own him GOD o'er all, for ever bleſt;\nFrom NOrth to South he ſhall extend his ſway,\nAnd long-loſt ISRAEL ſhall his call obey; i Fall at his feet, renouncing legal pride,\nAnd glory in a SAVIOUR crucified. ſi\nTHEN ſhall fair FREDOM rear her throne on high,\nAnd mortals prove the joys of Liberty;\nNot bodies only, but th' immortal mind,\nIn chains, by Sin and Satan, long confin'd,\n. Shall from their dread captivity be freed\nFreed by the SON, they muſt be free indeed.\nThe Goſpel's ſilver trump proclaims the day\nOf free ſalvation; ſee the lawful prey\nSnatch'd fronſ the dragon's jaws, by ſov'reign grace,\nTo dwell ſecure in all the ſweets of peace;\nSlaves from their iron bondage call'd, ariſe\nTo ſhare the noble freedom of the ſkies;\nExult in privileges freely given,\nAnd triumph as the Citizens of Heav'n. T HEN\n\n-- 43 of 57 --\n\nGALLIC LIBERTY.\nTHEN ſhall the ſeventh trumpet's glorious ſound\nAlarm, the ſkies, and ſhake the trembling ground;\nAngelic voices ſhall their ſongs prepare,\nTo uſher in the grand Sabbatic year\nWith burſts of loud applauſe, they ſing to thee,\nAnd ſhout thy fame, incarnate Deity!\nExult, ye Heav'ns! with mighty joy (they cry)\nSWell the glad triumphs of your King on high;\nWith Hallelujahs compaſs round his throne,\nIn ſolemn anthems make his wondersknown:\nFor the LORD GOD OMNlPOTENT appears\nIn robes of majeſty; the crown he wears,\nAnd reigns o'er all ſupreme, high rears his throne,\nAnd calls the Kingdoms of the earth his own;\nThey bow to JESU's ſteptre, and adore ;\nHe reigns, and he ſhall reign for ever more.\nJuſt are thy judgments, mighty King; thy pow'r\nHath pour'd deſtruction On the ſcarlet whore;\nThy truth ſhalltriumph, and thy Goſpel ſpread,\nTill time ſhall ceaſe, and Death itſelf is dead.\nThen, at thy potent word, diſſolv'd in fire,\nThe Heav'ns ſhall melt, the Univerſe expire:\nBut from its aſhes ſee a phoenix riſe,\nAn unpolluted earth, and purer ſkies ; -\nWhere dwelleth righteouſneſs, there Saints ſhall ſing\nThe matchleſs triumphs 'of their matchleſs King;\nThere perfect holineſs, and perfect peace, ,\nShall fill their boſoms with conſumate bliſs; '\t' Their\n\n-- 44 of 57 --\n\n36 ct GALLIC LIBERTY.\n.-m-5\"'-\".-.-'_-_.-._-.\n. ' l\nTheir GOD their temple, ſun, and great reward,\nAnd they the ranſom'd People of the LORD'.\nWhile Heav'n and Earth ſhall ſing triumphant grace,\nIn one orand chorus of eternal raiſe.\tO\nTHIS is the ſong of Heav'n ; but Saints below\nCatch the glad theme, intenſe deſires flow\nIn Sion's boſom for the happy day,\nWhen ſin and ſorrow ſhall be done away;\nShe longs to ſee her SAVIOUR's name ador'd,\nAnd all the Nations call her Jesus LORD;\nShe longs to ſee his chariot wheels appear,\nHis regal enſign flaming in the air,\nAt his' right hand to take her pompous place,\nAnd ſee her Heaven in his ſmiling face.\nIN that great day, how ſhall his foes appear i\nStruck dumb with terror and appall'd with fear!\nThe rich, the poor, the tyrant, and the ſlave,\nCall'd from their ſilent ſlumbers in the grave,\nBefore MtssrAH's bar to ſtand, and he'ar\nHis awful lips their ſinaldoom declare.\nProud Uribelief ſhall ſtop her mouth, 'and ſee\nThe Man who died upon th' accurſed tree\nIn all the ſplendours of a GOD ſhine forth,\nAnd groan beneath the vengeance of his wrath.\nAll who \"uſe his golden ſceptre's ſway,\nCruſh'd by his rod in that tremenduous day,\n-:i'.* Shall\n\n-- 45 of 57 --\n\nGALLIC LlBERTY. 37\nShall hear the gentle Lamb's meek voice no more 5\nBut Judah's Lion, With his awful roar,\nTheir ſouls transfixing in eternal vvoe, -\nNor can they fly, or from his preſence go.\nIn vain to tocks and hills they call' for aid,\nThe falling mountains can afford no ſhade ;\nAmidſt diſſolving worlds no ſafety's found,\nThe Heav'ns depart, and all is horror round ;\nFierce lightnings, iſſuing from the burning throne,\nDrive the accurſed crew of rebels down,\nTo dwell with black Deſpair, to howl and weep\nEternal ages in the fiery deep I\nO think of this in time, ye Sons of Men!\nLeſt ye repent too late, and tremble then,\nWhen awful Juſtice ſhuts Compaffion's door, '\nAnd Nlercy, meek-ey'd Mercy, reigns no more.\nTHE Spirit and the Waiting Bride ſay, Come;\nO come, Redeemer, from thy heav'nly homelCome in thy kingdom of Almighty Grace, i\nCome and receive us to thy ſweet embrace!\nThy Dove, that wanders in the,wildernefs,\nLongs to put on her glorious marriage dreſs;\nFrom thy kind hand to take the promis'd crown,\nAnd humbly at thy footſtool lay it down:\nShe ſighs for thee, ſhe longs to tune her lyre,\nAndjoin her ſongs with the ſeraphic choir;\n\n-- 46 of 57 --\n\n, 28 GALLIC LIBERTY.\nTo raiſe her joyful notes, their notes above, V\nAnd ſing the wonders of redeeming love; *'\nWorthy the Lamb, the Lamb for Sinners ſlain,\nTo fill his Father's throne, and ever reign 3\nWhile Saints and Angels ſiſing immortal praiſe,\nAnd view his glories thro' eternal days !\nTHE END\n,AJ _. _ - WMMWA\n\n-- 47 of 57 --\n\n-- 48 of 57 --\n\n**__\n\n-- 49 of 57 --\n\n-- 50 of 57 --\n\n-- 51 of 57 --\n\n-- 52 of 57 --\n\n-- 53 of 57 --\n\nRECORD OF TREATNENT, EXTRACTlON ETC.\nShe'fmark: \\(62>')_ ob 'O/ SHED'ODZ ®\nS&P Ref No.\nMicrofilm No. Pb And ZTiM-Q.\nDate Particulars pH Before or Existing pH After\n4 - A? N\\A\nDeacidification\nAdhesives\nWCM Wrzgu BITE , QnJN-L BKLL.\nLined / Laminated\nChemicals l Solvents\nCoverTreatment\nOther Remarks\nA a .\n\\\\5\\-$\\*\\ All) ( 'I C\\(L;\\_c\\_ .',\n\n-- 54 of 57 --\n\n-- 55 of 57 --\n\nPRESERVATION SERVICE\nSHELFMARK .l. . lq\nTHIS BOOK HAS BEEN\nMlCROFILMED ( IQQS' )\nMICROFILM No?fl.m.'£.9..\n37C' t+z\n\n-- 56 of 57 --\n\n-- 57 of 57 --"
}
